Workbook

Sheet Main
B1: Sq.ft. | C1: Sq.m.
A2: REU | B2: IN-CHEK2
A3: Chargeable Office Area | B3: 9515 | C3: =B3/10.764 -> 883.96507
A4: Agreement Start Date | B4: 46113
A5: Agreement End Date | B5: 47573
A6: Agreement Period | B6: =(B5-B4)/365 -> 4
A7: Quoted Rentals | B7: 120
A8: Quoted CAM | B8: 15.48
A9: Security Deposit | B9: 11418000
A10: Capex | B10: 2400000
A11: PM cost Over lease period
A12: Cost of Capital | B12: 0.15
A13: Imputed Interest | B13: 0.075
A14: Escalation Clause Rent | B14: 15% every 3 years
A15: Escalation Clause CAM | B15: 5% every years
A16: Maintenance Security Deposit (number of months)
A17: Addnl.Deposit -energy(Refundable) | B17: 500000

Sheet Security Deposit
B2: Security Deposit | C2: Interest | D2: Remark
A3: Fitout Deposit | B3: 0 | C3: =+B3*Main!B12/12*33.5 -> 0
A4: Security deposit | B4: =Main!B9 -> 11418000 | C4: =+B4*B9/12*D4 -> 10276200 | D4: ='Lease Rent'!H22 -> 72
A5: Additional deposit | B5: ='Lease Rent'!J31 * Main!B3 * Main!B16 -> 0 | C5: =+B5*Main!B12/12*D5 -> 0 | D5: =D4 -> 72
A6: Additional deposit (Electricity) | B6: =Main!B17 -> 500000 | C6: =+B6*B9*3 -> 225000
A7: Total | B7: =SUM(B3:B6) -> 11918000 | C7: =SUM(C3:C6) -> 10501200 | D7: =AVERAGE(D4:D6) -> 72
A8: Area sqft | B8: =Main!B3 -> 9515
A9: Rate for Carrying Cost | B9: =Main!B12 -> 0.15
A10: Term Period in Months | B10: ='Lease Rent'!H22 -> 72
A11: Rate per Sqft | C11: =C7/(B8*B10) -> 15.328429
A15: ARO working | B15: Per sqft | C15: Per sqmt
A16: Area (Sqft) | B16: =Main!B3 -> 9515
A17: ARO Rate (as on 30-09-2017) | B17: =IF(B16<50000,82.6,62.72) -> 82.6 | C17: =B17*10.764 -> 889.1064
A18: Total ARO Cost | B18: =B16*B17 -> 785939 | C18: =B18/B10 -> 10915.819
A19: Conversion Factor | B19: =C18/B16 -> 1.1472222

Sheet Lease Rent
G13: Rentals
G14: Year | H14: Months | I14: Rentals | J14: CAM | K14: Total
G15: 2026 | H15: =SUMIF($A$31:$A$1048576,$G15,$D$31:$D$102) -> 9 | I15: =SUMIF($A$31:$A$1048576,$G15,$K$31:$K$102) -> 10276200 | J15: =SUMIF($A$31:$A$1048576,$G15,$L$31:$L$102) -> 1325629.8 | K15: =I15+J15 -> 11601830
G16: =G15+1 -> 2027 | H16: =SUMIF($A$31:$A$1048576,$G16,$D$31:$D$102) -> 12 | I16: =SUMIF($A$31:$A$1048576,$G16,$K$31:$K$102) -> 13701600 | J16: =SUMIF($A$31:$A$1048576,$G16,$L$31:$L$102) -> 1826423.3 | K16: =I16+J16 -> 15528023
G17: =G16+1 -> 2028 | H17: =SUMIF($A$31:$A$1048576,$G17,$D$31:$D$102) -> 12 | I17: =SUMIF($A$31:$A$1048576,$G17,$K$31:$K$102) -> 13701600 | J17: =SUMIF($A$31:$A$1048576,$G17,$L$31:$L$102) -> 1917744.4 | K17: =I17+J17 -> 15619344
G18: =G17+1 -> 2029 | H18: =SUMIF($A$31:$A$1048576,$G18,$D$31:$D$102) -> 12 | I18: =SUMIF($A$31:$A$1048576,$G18,$K$31:$K$102) -> 15243030 | J18: =SUMIF($A$31:$A$1048576,$G18,$L$31:$L$102) -> 2021751.1 | K18: =I18+J18 -> 17264781
G19: =G18+1 -> 2030 | H19: =SUMIF($A$31:$A$1048576,$G19,$D$31:$D$102) -> 12 | I19: =SUMIF($A$31:$A$1048576,$G19,$K$31:$K$102) -> 15756840 | J19: =SUMIF($A$31:$A$1048576,$G19,$L$31:$L$102) -> 2114313.2 | K19: =I19+J19 -> 17871153
G20: =G19+1 -> 2031 | H20: =SUMIF($A$31:$A$1048576,$G20,$D$31:$D$102) -> 12 | I20: =SUMIF($A$31:$A$1048576,$G20,$K$31:$K$102) -> 15756840 | J20: =SUMIF($A$31:$A$1048576,$G20,$L$31:$L$102) -> 2220028.9 | K20: =I20+J20 -> 17976869
G21: =G20+1 -> 2032 | H21: =SUMIF($A$31:$A$1048576,$G21,$D$31:$D$102) -> 3 | I21: =SUMIF($A$31:$A$1048576,$G21,$K$31:$K$102) -> 3939210 | J21: =SUMIF($A$31:$A$1048576,$G21,$L$31:$L$102) -> 563958.96 | K21: =I21+J21 -> 4503169
H22: =SUM(H15:H21) -> 72 | I22: =SUM(I15:I21) -> 88375320 | J22: =SUM(J15:J21) -> 11989850 | K22: =SUM(K15:K21) -> 1.0036517e+08
A30: Year | B30: From | C30: To | D30: Months | E30: Area in SQF | F30: Area in SQM | G30: Escalation | H30: Rental | I30: Car Parks per # | J30: CAM | K30: Rental SQM | L30: CAM SQM | M30: Total | N30: Rentals | O30: CAM
A31: 2026 | B31: 46023 | C31: =B31+30 -> 46053 | D31: 1 | E31: =Main!B3 -> 9515 | F31: =Main!C3 -> 883.96507 | H31: =120 -> 120 | J31: =15.48 -> 15.48 | K31: =H31*E31 -> 1141800 | L31: =J31*E31 -> 147292.2 | M31: =I31+K31+L31 -> 1289092.2
A32: =A31 -> 2026 | B32: =C31+1 -> 46054 | C32: =B32+30-3 -> 46081 | D32: 1 | E32: 9515 | F32: 883.96507 | H32: 120 | J32: 15.48 | K32: =H32*E32 -> 1141800 | L32: =J32*E32 -> 147292.2 | M32: =I32+K32+L32 -> 1289092.2
A33: =A32 -> 2026 | B33: =C32+1 -> 46082 | C33: =B33+30 -> 46112 | D33: 1 | E33: =E32 -> 9515 | F33: =F32 -> 883.96507 | H33: 120 | J33: =J32 -> 15.48 | K33: =H33*E33 -> 1141800 | L33: =J33*E33 -> 147292.2 | M33: =I33+K33+L33 -> 1289092.2
A34: =A33 -> 2026 | B34: =C33+1 -> 46113 | C34: =B34+30-1 -> 46142 | D34: 1 | E34: =E33 -> 9515 | F34: =F33 -> 883.96507 | H34: 120 | J34: =J33 -> 15.48 | K34: =H34*E34 -> 1141800 | L34: =J34*E34 -> 147292.2 | M34: =I34+K34+L34 -> 1289092.2
A35: =A34 -> 2026 | B35: =C34+1 -> 46143 | C35: =B35+30 -> 46173 | D35: 1 | E35: =E34 -> 9515 | F35: =F34 -> 883.96507 | H35: 120 | J35: =J34 -> 15.48 | K35: =H35*E35 -> 1141800 | L35: =J35*E35 -> 147292.2 | M35: =I35+K35+L35 -> 1289092.2
A36: =A35 -> 2026 | B36: =C35+1 -> 46174 | C36: =B36+30-1 -> 46203 | D36: 1 | E36: =E35 -> 9515 | F36: =F35 -> 883.96507 | H36: 120 | J36: =J35 -> 15.48 | K36: =H36*E36 -> 1141800 | L36: =J36*E36 -> 147292.2 | M36: =I36+K36+L36 -> 1289092.2
A37: =A36 -> 2026 | B37: =C36+1 -> 46204 | C37: =B37+30-1 -> 46233 | D37: 1 | E37: =E36 -> 9515 | F37: =F36 -> 883.96507 | H37: 120 | J37: =J36 -> 15.48 | K37: =H37*E37 -> 1141800 | L37: =J37*E37 -> 147292.2 | M37: =I37+K37+L37 -> 1289092.2
A38: =A37 -> 2026 | B38: =C37+1 -> 46234 | C38: =B38+30 -> 46264 | D38: 1 | E38: =E37 -> 9515 | F38: =F37 -> 883.96507 | H38: 120 | J38: =J37 -> 15.48 | K38: =H38*E38 -> 1141800 | L38: =J38*E38 -> 147292.2 | M38: =I38+K38+L38 -> 1289092.2
A39: =A38 -> 2026 | B39: =C38+1 -> 46265 | C39: =B39+30 -> 46295 | D39: 1 | E39: =E38 -> 9515 | F39: =F38 -> 883.96507 | H39: 120 | J39: =J38 -> 15.48 | K39: =H39*E39 -> 1141800 | L39: =J39*E39 -> 147292.2 | M39: =I39+K39+L39 -> 1289092.2 | N39: =SUM(K31:K39) -> 10276200 | O39: =SUM(L31:L39) -> 1325629.8
A40: =A39+1 -> 2027 | B40: =C39+1 -> 46296 | C40: =B40+30 -> 46326 | D40: 1 | E40: =E39 -> 9515 | F40: =F39 -> 883.96507 | H40: 120 | J40: =J39 -> 15.48 | K40: =H40*E40 -> 1141800 | L40: =J40*E40 -> 147292.2 | M40: =I40+K40+L40 -> 1289092.2
A41: =A40 -> 2027 | B41: =C40+1 -> 46327 | C41: =B41+30-1 -> 46356 | D41: 1 | E41: =E40 -> 9515 | F41: =F40 -> 883.96507 | H41: 120 | J41: =J40 -> 15.48 | K41: =H41*E41 -> 1141800 | L41: =J41*E41 -> 147292.2 | M41: =I41+K41+L41 -> 1289092.2
A42: =A41 -> 2027 | B42: =C41+1 -> 46357 | C42: =B42+30 -> 46387 | D42: 1 | E42: =E41 -> 9515 | F42: =F41 -> 883.96507 | H42: 120 | J42: =J41 -> 15.48 | K42: =H42*E42 -> 1141800 | L42: =J42*E42 -> 147292.2 | M42: =I42+K42+L42 -> 1289092.2
A43: =A42 -> 2027 | B43: =C42+1 -> 46388 | C43: =B43+30 -> 46418 | D43: 1 | E43: =E42 -> 9515 | F43: =F42 -> 883.96507 | H43: 120 | J43: =J42 -> 15.48 | K43: =H43*E43 -> 1141800 | L43: =J43*E43 -> 147292.2 | M43: =I43+K43+L43 -> 1289092.2
A44: =A43 -> 2027 | B44: =C43+1 -> 46419 | C44: =B44+30-3 -> 46446 | D44: 1 | E44: =E43 -> 9515 | F44: =F43 -> 883.96507 | H44: 120 | J44: =J43*1.05 -> 16.254 | K44: =H44*E44 -> 1141800 | L44: =J44*E44 -> 154656.81 | M44: =I44+K44+L44 -> 1296456.8
A45: =A44 -> 2027 | B45: =C44+1 -> 46447 | C45: =B45+30 -> 46477 | D45: 1 | E45: =E44 -> 9515 | F45: =F44 -> 883.96507 | H45: 120 | J45: =J44 -> 16.254 | K45: =H45*E45 -> 1141800 | L45: =J45*E45 -> 154656.81 | M45: =I45+K45+L45 -> 1296456.8
A46: =A45 -> 2027 | B46: =C45+1 -> 46478 | C46: =B46+30-1 -> 46507 | D46: 1 | E46: =E45 -> 9515 | F46: =F45 -> 883.96507 | H46: 120 | J46: =J45 -> 16.254 | K46: =H46*E46 -> 1141800 | L46: =J46*E46 -> 154656.81 | M46: =I46+K46+L46 -> 1296456.8
A47: =A46 -> 2027 | B47: =C46+1 -> 46508 | C47: =B47+30 -> 46538 | D47: 1 | E47: =E46 -> 9515 | F47: =F46 -> 883.96507 | H47: 120 | J47: =J46 -> 16.254 | K47: =H47*E47 -> 1141800 | L47: =J47*E47 -> 154656.81 | M47: =I47+K47+L47 -> 1296456.8
A48: =A47 -> 2027 | B48: =C47+1 -> 46539 | C48: =B48+30-1 -> 46568 | D48: 1 | E48: =E47 -> 9515 | F48: =F47 -> 883.96507 | H48: 120 | J48: =J47 -> 16.254 | K48: =H48*E48 -> 1141800 | L48: =J48*E48 -> 154656.81 | M48: =I48+K48+L48 -> 1296456.8
A49: =A48 -> 2027 | B49: =C48+1 -> 46569 | C49: =B49+30 -> 46599 | D49: 1 | E49: =E48 -> 9515 | F49: =F48 -> 883.96507 | H49: 120 | J49: =J48 -> 16.254 | K49: =H49*E49 -> 1141800 | L49: =J49*E49 -> 154656.81 | M49: =I49+K49+L49 -> 1296456.8
A50: =A49 -> 2027 | B50: =C49+1 -> 46600 | C50: =B50+30 -> 46630 | D50: 1 | E50: =E49 -> 9515 | F50: =F49 -> 883.96507 | H50: 120 | J50: =J49 -> 16.254 | K50: =H50*E50 -> 1141800 | L50: =J50*E50 -> 154656.81 | M50: =I50+K50+L50 -> 1296456.8
A51: =A50 -> 2027 | B51: =C50+1 -> 46631 | C51: =B51+30-1 -> 46660 | D51: 1 | E51: =E50 -> 9515 | F51: =F50 -> 883.96507 | H51: 120 | J51: =J50 -> 16.254 | K51: =H51*E51 -> 1141800 | L51: =J51*E51 -> 154656.81 | M51: =I51+K51+L51 -> 1296456.8 | N51: =SUM(K40:K51) -> 13701600 | O51: =SUM(L40:L51) -> 1826423.3
A52: =A51+1 -> 2028 | B52: =C51+1 -> 46661 | C52: =B52+30 -> 46691 | D52: 1 | E52: =E51 -> 9515 | F52: =F51 -> 883.96507 | H52: 120 | J52: =J51 -> 16.254 | K52: =H52*E52 -> 1141800 | L52: =J52*E52 -> 154656.81 | M52: =I52+K52+L52 -> 1296456.8
A53: =A52 -> 2028 | B53: =C52+1 -> 46692 | C53: =B53+30-1 -> 46721 | D53: 1 | E53: =E52 -> 9515 | F53: =F52 -> 883.96507 | H53: 120 | J53: =J52 -> 16.254 | K53: =H53*E53 -> 1141800 | L53: =J53*E53 -> 154656.81 | M53: =I53+K53+L53 -> 1296456.8
A54: =A53 -> 2028 | B54: =C53+1 -> 46722 | C54: =B54+30 -> 46752 | D54: 1 | E54: =E53 -> 9515 | F54: =F53 -> 883.96507 | H54: 120 | J54: =J53 -> 16.254 | K54: =H54*E54 -> 1141800 | L54: =J54*E54 -> 154656.81 | M54: =I54+K54+L54 -> 1296456.8
A55: =A54 -> 2028 | B55: =C54+1 -> 46753 | C55: =B55+30 -> 46783 | D55: 1 | E55: =E54 -> 9515 | F55: =F54 -> 883.96507 | H55: 120 | J55: =J54 -> 16.254 | K55: =H55*E55 -> 1141800 | L55: =J55*E55 -> 154656.81 | M55: =I55+K55+L55 -> 1296456.8
A56: =A55 -> 2028 | B56: =C55+1 -> 46784 | C56: =B56+30-2 -> 46812 | D56: 1 | E56: =E55 -> 9515 | F56: =F55 -> 883.96507 | H56: 120 | J56: =J55*1.05 -> 17.0667 | K56: =H56*E56 -> 1141800 | L56: =J56*E56 -> 162389.65 | M56: =I56+K56+L56 -> 1304189.7
A57: =A56 -> 2028 | B57: =C56+1 -> 46813 | C57: =B57+30 -> 46843 | D57: 1 | E57: =E56 -> 9515 | F57: =F56 -> 883.96507 | H57: 120 | J57: =J56 -> 17.0667 | K57: =H57*E57 -> 1141800 | L57: =J57*E57 -> 162389.65 | M57: =I57+K57+L57 -> 1304189.7
A58: =A57 -> 2028 | B58: =C57+1 -> 46844 | C58: =B58+30-1 -> 46873 | D58: 1 | E58: =E57 -> 9515 | F58: =F57 -> 883.96507 | H58: 120 | J58: =J57 -> 17.0667 | K58: =H58*E58 -> 1141800 | L58: =J58*E58 -> 162389.65 | M58: =I58+K58+L58 -> 1304189.7
A59: =A58 -> 2028 | B59: =C58+1 -> 46874 | C59: =B59+30 -> 46904 | D59: 1 | E59: =E58 -> 9515 | F59: =F58 -> 883.96507 | H59: 120 | J59: =J58 -> 17.0667 | K59: =H59*E59 -> 1141800 | L59: =J59*E59 -> 162389.65 | M59: =I59+K59+L59 -> 1304189.7
A60: =A59 -> 2028 | B60: =C59+1 -> 46905 | C60: =B60+30-1 -> 46934 | D60: 1 | E60: =E59 -> 9515 | F60: =F59 -> 883.96507 | H60: 120 | J60: =J59 -> 17.0667 | K60: =H60*E60 -> 1141800 | L60: =J60*E60 -> 162389.65 | M60: =I60+K60+L60 -> 1304189.7
A61: =A60 -> 2028 | B61: =C60+1 -> 46935 | C61: =B61+30 -> 46965 | D61: 1 | E61: =E60 -> 9515 | F61: =F60 -> 883.96507 | H61: 120 | J61: =J60 -> 17.0667 | K61: =H61*E61 -> 1141800 | L61: =J61*E61 -> 162389.65 | M61: =I61+K61+L61 -> 1304189.7
A62: =A61 -> 2028 | B62: =C61+1 -> 46966 | C62: =B62+30 -> 46996 | D62: 1 | E62: =E61 -> 9515 | F62: =F61 -> 883.96507 | H62: 120 | J62: =J61 -> 17.0667 | K62: =H62*E62 -> 1141800 | L62: =J62*E62 -> 162389.65 | M62: =I62+K62+L62 -> 1304189.7
A63: =A62 -> 2028 | B63: =C62+1 -> 46997 | C63: =B63+30-1 -> 47026 | D63: 1 | E63: =E62 -> 9515 | F63: =F62 -> 883.96507 | H63: 120 | J63: =J62 -> 17.0667 | K63: =H63*E63 -> 1141800 | L63: =J63*E63 -> 162389.65 | M63: =I63+K63+L63 -> 1304189.7 | N63: =SUM(K52:K63) -> 13701600 | O63: =SUM(L52:L63) -> 1917744.4
A64: =2028+1 -> 2029 | B64: =C63+1 -> 47027 | C64: =B64+30 -> 47057 | D64: 1 | E64: =E63 -> 9515 | F64: =F63 -> 883.96507 | H64: 120 | J64: =J63 -> 17.0667 | K64: =H64*E64 -> 1141800 | L64: =J64*E64 -> 162389.65 | M64: =I64+K64+L64 -> 1304189.7
A65: =A64 -> 2029 | B65: =C64+1 -> 47058 | C65: =B65+30-1 -> 47087 | D65: 1 | E65: =E64 -> 9515 | F65: =F64 -> 883.96507 | H65: 120 | J65: =J64 -> 17.0667 | K65: =H65*E65 -> 1141800 | L65: =J65*E65 -> 162389.65 | M65: =I65+K65+L65 -> 1304189.7
A66: =A65 -> 2029 | B66: =C65+1 -> 47088 | C66: =B66+30 -> 47118 | D66: 1 | E66: =E65 -> 9515 | F66: =F65 -> 883.96507 | H66: 120 | J66: =J65 -> 17.0667 | K66: =H66*E66 -> 1141800 | L66: =J66*E66 -> 162389.65 | M66: =I66+K66+L66 -> 1304189.7
A67: =A66 -> 2029 | B67: =C66+1 -> 47119 | C67: =B67+30 -> 47149 | D67: 1 | E67: =E66 -> 9515 | F67: =F66 -> 883.96507 | H67: =H66*1.15 -> 138 | J67: =J66*1.05 -> 17.920035 | K67: =H67*E67 -> 1313070 | L67: =J67*E67 -> 170509.13 | M67: =I67+K67+L67 -> 1483579.1
A68: =A67 -> 2029 | B68: =C67+1 -> 47150 | C68: =B68+30-3 -> 47177 | D68: 1 | E68: =E67 -> 9515 | F68: =F67 -> 883.96507 | H68: =H67 -> 138 | J68: =J67 -> 17.920035 | K68: =H68*E68 -> 1313070 | L68: =J68*E68 -> 170509.13 | M68: =I68+K68+L68 -> 1483579.1
A69: =A68 -> 2029 | B69: =C68+1 -> 47178 | C69: =B69+30 -> 47208 | D69: 1 | E69: =E68 -> 9515 | F69: =F68 -> 883.96507 | H69: =H68 -> 138 | J69: =J68 -> 17.920035 | K69: =H69*E69 -> 1313070 | L69: =J69*E69 -> 170509.13 | M69: =I69+K69+L69 -> 1483579.1
A70: =A69 -> 2029 | B70: =C69+1 -> 47209 | C70: =B70+30-1 -> 47238 | D70: 1 | E70: =E69 -> 9515 | F70: =F69 -> 883.96507 | H70: =H69 -> 138 | J70: =J69 -> 17.920035 | K70: =H70*E70 -> 1313070 | L70: =J70*E70 -> 170509.13 | M70: =I70+K70+L70 -> 1483579.1
A71: =A70 -> 2029 | B71: =C70+1 -> 47239 | C71: =B71+30 -> 47269 | D71: 1 | E71: =E70 -> 9515 | F71: =F70 -> 883.96507 | H71: =H70 -> 138 | J71: =J70 -> 17.920035 | K71: =H71*E71 -> 1313070 | L71: =J71*E71 -> 170509.13 | M71: =I71+K71+L71 -> 1483579.1
A72: =A71 -> 2029 | B72: =C71+1 -> 47270 | C72: =B72+30-1 -> 47299 | D72: 1 | E72: =E71 -> 9515 | F72: =F71 -> 883.96507 | H72: =H71 -> 138 | J72: =J71 -> 17.920035 | K72: =H72*E72 -> 1313070 | L72: =J72*E72 -> 170509.13 | M72: =I72+K72+L72 -> 1483579.1
A73: =A72 -> 2029 | B73: =C72+1 -> 47300 | C73: =B73+30 -> 47330 | D73: 1 | E73: =E72 -> 9515 | F73: =F72 -> 883.96507 | H73: =H72 -> 138 | J73: =J72 -> 17.920035 | K73: =H73*E73 -> 1313070 | L73: =J73*E73 -> 170509.13 | M73: =I73+K73+L73 -> 1483579.1
A74: =A73 -> 2029 | B74: =C73+1 -> 47331 | C74: =B74+30 -> 47361 | D74: 1 | E74: =E73 -> 9515 | F74: =F73 -> 883.96507 | H74: =H73 -> 138 | J74: =J73 -> 17.920035 | K74: =H74*E74 -> 1313070 | L74: =J74*E74 -> 170509.13 | M74: =I74+K74+L74 -> 1483579.1
A75: =A74 -> 2029 | B75: =C74+1 -> 47362 | C75: =B75+30-1 -> 47391 | D75: 1 | E75: =E74 -> 9515 | F75: =F74 -> 883.96507 | H75: =H74 -> 138 | J75: =J74 -> 17.920035 | K75: =H75*E75 -> 1313070 | L75: =J75*E75 -> 170509.13 | M75: =I75+K75+L75 -> 1483579.1 | N75: =SUM(K64:K75) -> 15243030 | O75: =SUM(L64:L75) -> 2021751.1
A76: =A75+1 -> 2030 | B76: =C75+1 -> 47392 | C76: =B76+30 -> 47422 | D76: 1 | E76: =E75 -> 9515 | F76: =F75 -> 883.96507 | H76: =H75 -> 138 | J76: =J75 -> 17.920035 | K76: =H76*E76 -> 1313070 | L76: =J76*E76 -> 170509.13 | M76: =I76+K76+L76 -> 1483579.1
A77: =A76 -> 2030 | B77: =C76+1 -> 47423 | C77: =B77+30-1 -> 47452 | D77: 1 | E77: =E76 -> 9515 | F77: =F76 -> 883.96507 | H77: =H76 -> 138 | J77: =J76 -> 17.920035 | K77: =H77*E77 -> 1313070 | L77: =J77*E77 -> 170509.13 | M77: =I77+K77+L77 -> 1483579.1
A78: =A77 -> 2030 | B78: =C77+1 -> 47453 | C78: =B78+30 -> 47483 | D78: 1 | E78: =E77 -> 9515 | F78: =F77 -> 883.96507 | H78: =H77 -> 138 | J78: =J77 -> 17.920035 | K78: =H78*E78 -> 1313070 | L78: =J78*E78 -> 170509.13 | M78: =I78+K78+L78 -> 1483579.1
A79: =A78 -> 2030 | B79: =C78+1 -> 47484 | C79: =B79+30 -> 47514 | D79: 1 | E79: =E78 -> 9515 | F79: =F78 -> 883.96507 | H79: =H78 -> 138 | J79: =J78 -> 17.920035 | K79: =H79*E79 -> 1313070 | L79: =J79*E79 -> 170509.13 | M79: =I79+K79+L79 -> 1483579.1
A80: =A79 -> 2030 | B80: =C79+1 -> 47515 | C80: =B80+30-3 -> 47542 | D80: 1 | E80: =E79 -> 9515 | F80: =F79 -> 883.96507 | H80: =H79 -> 138 | J80: =J79*1.05 -> 18.816037 | K80: =H80*E80 -> 1313070 | L80: =J80*E80 -> 179034.59 | M80: =I80+K80+L80 -> 1492104.6
A81: =A80 -> 2030 | B81: =C80+1 -> 47543 | C81: =B81+30 -> 47573 | D81: 1 | E81: =E80 -> 9515 | F81: =F80 -> 883.96507 | H81: =H80 -> 138 | J81: =J80 -> 18.816037 | K81: =H81*E81 -> 1313070 | L81: =J81*E81 -> 179034.59 | M81: =I81+K81+L81 -> 1492104.6
A82: =A81 -> 2030 | B82: =C81+1 -> 47574 | C82: =B82+30-1 -> 47603 | D82: 1 | E82: =E81 -> 9515 | F82: =F81 -> 883.96507 | H82: =H81 -> 138 | J82: =J81 -> 18.816037 | K82: =H82*E82 -> 1313070 | L82: =J82*E82 -> 179034.59 | M82: =I82+K82+L82 -> 1492104.6
A83: =A82 -> 2030 | B83: =C82+1 -> 47604 | C83: =B83+30 -> 47634 | D83: 1 | E83: =E82 -> 9515 | F83: =F82 -> 883.96507 | H83: =H82 -> 138 | J83: =J82 -> 18.816037 | K83: =H83*E83 -> 1313070 | L83: =J83*E83 -> 179034.59 | M83: =I83+K83+L83 -> 1492104.6
A84: =A83 -> 2030 | B84: =C83+1 -> 47635 | C84: =B84+30-1 -> 47664 | D84: 1 | E84: =E83 -> 9515 | F84: =F83 -> 883.96507 | H84: =H83 -> 138 | J84: =J83 -> 18.816037 | K84: =H84*E84 -> 1313070 | L84: =J84*E84 -> 179034.59 | M84: =I84+K84+L84 -> 1492104.6
A85: =A84 -> 2030 | B85: =C84+1 -> 47665 | C85: =B85+30 -> 47695 | D85: 1 | E85: =E84 -> 9515 | F85: =F84 -> 883.96507 | H85: =H84 -> 138 | J85: =J84 -> 18.816037 | K85: =H85*E85 -> 1313070 | L85: =J85*E85 -> 179034.59 | M85: =I85+K85+L85 -> 1492104.6
A86: =A85 -> 2030 | B86: =C85+1 -> 47696 | C86: =B86+30 -> 47726 | D86: 1 | E86: =E85 -> 9515 | F86: =F85 -> 883.96507 | H86: =H85 -> 138 | J86: =J85 -> 18.816037 | K86: =H86*E86 -> 1313070 | L86: =J86*E86 -> 179034.59 | M86: =I86+K86+L86 -> 1492104.6
A87: =A86 -> 2030 | B87: =C86+1 -> 47727 | C87: =B87+30-1 -> 47756 | D87: 1 | E87: =E86 -> 9515 | F87: =F86 -> 883.96507 | H87: =H86 -> 138 | J87: =J86 -> 18.816037 | K87: =H87*E87 -> 1313070 | L87: =J87*E87 -> 179034.59 | M87: =I87+K87+L87 -> 1492104.6 | N87: =SUM(K76:K87) -> 15756840 | O87: =SUM(L76:L87) -> 2114313.2
A88: =A87+1 -> 2031 | B88: =C87+1 -> 47757 | C88: =B88+30 -> 47787 | D88: 1 | E88: =E87 -> 9515 | F88: =F87 -> 883.96507 | H88: =H87 -> 138 | J88: =J87 -> 18.816037 | K88: =H88*E88 -> 1313070 | L88: =J88*E88 -> 179034.59 | M88: =I88+K88+L88 -> 1492104.6
A89: =A88 -> 2031 | B89: =C88+1 -> 47788 | C89: =B89+30-1 -> 47817 | D89: 1 | E89: =E88 -> 9515 | F89: =F88 -> 883.96507 | H89: =H88 -> 138 | J89: =J88 -> 18.816037 | K89: =H89*E89 -> 1313070 | L89: =J89*E89 -> 179034.59 | M89: =I89+K89+L89 -> 1492104.6
A90: =A89 -> 2031 | B90: =C89+1 -> 47818 | C90: =B90+30 -> 47848 | D90: 1 | E90: =E89 -> 9515 | F90: =F89 -> 883.96507 | H90: =H89 -> 138 | J90: =J89 -> 18.816037 | K90: =H90*E90 -> 1313070 | L90: =J90*E90 -> 179034.59 | M90: =I90+K90+L90 -> 1492104.6
A91: =A90 -> 2031 | B91: =C90+1 -> 47849 | C91: =B91+30 -> 47879 | D91: 1 | E91: =E90 -> 9515 | F91: =F90 -> 883.96507 | H91: =H90 -> 138 | J91: =J90 -> 18.816037 | K91: =H91*E91 -> 1313070 | L91: =J91*E91 -> 179034.59 | M91: =I91+K91+L91 -> 1492104.6
A92: =A91 -> 2031 | B92: =C91+1 -> 47880 | C92: =B92+30-3 -> 47907 | D92: 1 | E92: =E91 -> 9515 | F92: =F91 -> 883.96507 | H92: =H91 -> 138 | J92: =J91*1.05 -> 19.756839 | K92: =H92*E92 -> 1313070 | L92: =J92*E92 -> 187986.32 | M92: =I92+K92+L92 -> 1501056.3
A93: =A92 -> 2031 | B93: =C92+1 -> 47908 | C93: =B93+30 -> 47938 | D93: 1 | E93: =E92 -> 9515 | F93: =F92 -> 883.96507 | H93: =H92 -> 138 | J93: =J92 -> 19.756839 | K93: =H93*E93 -> 1313070 | L93: =J93*E93 -> 187986.32 | M93: =I93+K93+L93 -> 1501056.3
A94: =A93 -> 2031 | B94: =C93+1 -> 47939 | C94: =B94+30-1 -> 47968 | D94: 1 | E94: =E93 -> 9515 | F94: =F93 -> 883.96507 | H94: =H93 -> 138 | J94: =J93 -> 19.756839 | K94: =H94*E94 -> 1313070 | L94: =J94*E94 -> 187986.32 | M94: =I94+K94+L94 -> 1501056.3
A95: =A94 -> 2031 | B95: =C94+1 -> 47969 | C95: =B95+30 -> 47999 | D95: 1 | E95: =E94 -> 9515 | F95: =F94 -> 883.96507 | H95: =H94 -> 138 | J95: =J94 -> 19.756839 | K95: =H95*E95 -> 1313070 | L95: =J95*E95 -> 187986.32 | M95: =I95+K95+L95 -> 1501056.3
A96: =A95 -> 2031 | B96: =C95+1 -> 48000 | C96: =B96+30-1 -> 48029 | D96: 1 | E96: =E95 -> 9515 | F96: =F95 -> 883.96507 | H96: =H95 -> 138 | J96: =J95 -> 19.756839 | K96: =H96*E96 -> 1313070 | L96: =J96*E96 -> 187986.32 | M96: =I96+K96+L96 -> 1501056.3
A97: =A96 -> 2031 | B97: =C96+1 -> 48030 | C97: =B97+30 -> 48060 | D97: 1 | E97: =E96 -> 9515 | F97: =F96 -> 883.96507 | H97: =H96 -> 138 | J97: =J96 -> 19.756839 | K97: =H97*E97 -> 1313070 | L97: =J97*E97 -> 187986.32 | M97: =I97+K97+L97 -> 1501056.3
A98: =A97 -> 2031 | B98: =C97+1 -> 48061 | C98: =B98+30 -> 48091 | D98: 1 | E98: =E97 -> 9515 | F98: =F97 -> 883.96507 | H98: =H97 -> 138 | J98: =J97 -> 19.756839 | K98: =H98*E98 -> 1313070 | L98: =J98*E98 -> 187986.32 | M98: =I98+K98+L98 -> 1501056.3
A99: =A98 -> 2031 | B99: =C98+1 -> 48092 | C99: =B99+30-1 -> 48121 | D99: 1 | E99: =E98 -> 9515 | F99: =F98 -> 883.96507 | H99: =H98 -> 138 | J99: =J98 -> 19.756839 | K99: =H99*E99 -> 1313070 | L99: =J99*E99 -> 187986.32 | M99: =I99+K99+L99 -> 1501056.3 | N99: =SUM(K88:K99) -> 15756840 | O99: =SUM(L88:L99) -> 2220028.9
A100: =A99+1 -> 2032 | B100: =C99+1 -> 48122 | C100: =B100+30 -> 48152 | D100: 1 | E100: =E99 -> 9515 | F100: =F99 -> 883.96507 | H100: =H99 -> 138 | J100: =J99 -> 19.756839 | K100: =H100*E100 -> 1313070 | L100: =J100*E100 -> 187986.32 | M100: =I100+K100+L100 -> 1501056.3
A101: =A100 -> 2032 | B101: =C100+1 -> 48153 | C101: =B101+30-1 -> 48182 | D101: 1 | E101: =E100 -> 9515 | F101: =F100 -> 883.96507 | H101: =H100 -> 138 | J101: =J100 -> 19.756839 | K101: =H101*E101 -> 1313070 | L101: =J101*E101 -> 187986.32 | M101: =I101+K101+L101 -> 1501056.3
A102: =A101 -> 2032 | B102: =C101+1 -> 48183 | C102: =B102+30 -> 48213 | D102: 1 | E102: =E101 -> 9515 | F102: =F101 -> 883.96507 | H102: =H101 -> 138 | J102: =J101 -> 19.756839 | K102: =H102*E102 -> 1313070 | L102: =J102*E102 -> 187986.32 | M102: =I102+K102+L102 -> 1501056.3 | N102: =SUM(K100:K102) -> 3939210 | O102: =SUM(L100:L102) -> 563958.96
K103: =SUM(K31:K102) -> 88375320 | L103: =SUM(L31:L102) -> 11989850 | M103: =SUM(M31:M102) -> 1.0036517e+08 | N103: =SUM(N31:N102) -> 88375320 | O103: =SUM(O31:O102) -> 11989850
